{
  "scenario": {
    "shape": [38, 22],
    "origin": [0, 0],
    "wrapped": false
  },
  "cells": {
    "default": {
      "delay": "inertial",
      "model": "bimsim",
      "state": { 
        "type": 3,
        "temperature": 22.50,
        "sensor": false
      },
      "neighborhood": [
        { "type": "moore", "range": 4 }
      ]
    },
    "empty_cold_0": {
      "state": { 
        "type": 0 
      }
    },
    "empty_cold_1": {
      "state": { 
        "type": 1 
      }
    },
    "empty_cold_2": {
      "state": { 
        "type": 2 
      }
    },
    "empty_ok_3": {
      "state": { 
        "type": 3 
      }
    },
    "empty_hot_4": {
      "state": { 
        "type": 4 
      }
    },
    "empty_hot_5": {
      "state": { 
        "type": 5 
      }
    },
    "empty_hot_6": {
      "state": { 
        "type": 6 
      }
    },
    "occupant_comfortable": {
      "state": { 
        "type": 7
      },
      "cell_map": [ 
                          [11, 2], [17, 2], [20, 2], [26, 2], [29, 2], [35, 2],
                 [ 8, 5], [11, 5], [17, 5], [20, 5], [26, 5], [29, 5], [35, 5],
                 [ 8, 8], [11, 8], [17, 8], [20, 8], [26, 8], [29, 8], [35, 8],
        [ 2,13], [ 8,13], [11,13], [17,13], [20,13], [26,13], [29,13], [35,13],
        [ 2,16], [ 8,16], [11,16], [17,16], [20,16], [26,16], [29,16], [35,16],
        [ 2,19], [ 8,19], [11,19], [17,19], [20,19], [26,19], [29,19], [35,19]
      ]
    },
    "occupant_uncomfortable": {
      "state": { 
        "type": 8
      }
    },
    "heater_on": {
      "state": { 
        "type": 9,
        "sensor": true
      }
    },
    "heater_off": {
      "state": { 
        "type": 10,
        "sensor": true
      },
      "cell_map": [ 
        [ 5, 5], [14, 5], [23, 5], [32, 5],
        [ 5,16], [14,16], [23,16], [32,16]
      ]
    },
    "wall": {
      "state": { 
        "type": 11
      },
      "cell_map": [ 

        [ 0, 0], [ 1, 0], [ 2, 0], [ 3, 0], [ 4, 0],          [ 6, 0], [ 7, 0], [ 8, 0], [ 9, 0], [10, 0], [11, 0], [12, 0], [13, 0],          [15, 0], [16, 0], [17, 0], [18, 0], [19, 0], [20, 0], [21, 0], [22, 0],          [24, 0], [25, 0], [26, 0], [27, 0], [28, 0], [29, 0], [30, 0], [31, 0],          [33, 0], [34, 0], [35, 0], [36, 0], [37, 0], 
        [ 0, 1],                                                                                                                                                                                                                                                                                                                                     [37, 1], 
        [ 0, 2],                                                                                                                                                                                                                                                                                                                                     [37, 2],
        [ 0, 3],                                                                                                                                                                                                                                                                                                                                     [37, 3], 
        [ 0, 4],                                                                                                                                                                                                                                                                                                                                     [37, 4], 
        [ 0, 5],                                                                                                                                                                                                                                                                                                                                     [37, 5], 
        [ 0, 6],                                                                                                                                                                                                                                                                                                                                     [37, 6], 
        [ 0, 7],                                                                                                                                                                                                                                                                                                                                     [37, 7], 
        [ 0, 8],                                                                                                                                                                                                                                                                                                                                     [37, 8], 
        [ 0, 9],                                                                                                                                                                                                                                                                                                                                     [37, 9], 
                                                                                                                                                                                                                                                                                                                                                              
                                                                                                                                                                                                                                                                                                                                                              
        [ 0,12],                                                                                                                                                                                                                                                                                                                                     [37,12], 
        [ 0,13],                                                                                                                                                                                                                                                                                                                                     [37,13], 
        [ 0,14],                                                                                                                                                                                                                                                                                                                                     [37,14], 
        [ 0,15],                                                                                                                                                                                                                                                                                                                                     [37,15], 
        [ 0,16],                                                                                                                                                                                                                                                                                                                                     [37,16], 
        [ 0,17],                                                                                                                                                                                                                                                                                                                                     [37,17], 
        [ 0,18],                                                                                                                                                                                                                                                                                                                                     [37,18], 
        [ 0,19],                                                                                                                                                                                                                                                                                                                                     [37,19], 
        [ 0,20],                                                                                                                                                                                                                                                                                                                                     [37,20], 
        [ 0,21], [ 1,21], [ 2,21], [ 3,21], [ 4,21],          [ 6,21], [ 7,21], [ 8,21], [ 9,21], [10,21], [11,21], [12,21], [13,21],          [15,21], [16,21], [17,21], [18,21], [19,21], [20,21], [21,21], [22,21],          [24,21], [25,21], [26,21], [27,21], [28,21], [29,21], [30,21], [31,21],          [33,21], [34,21], [35,21], [36,21], [37,21]
      ]
    },
    "window": {
      "state": { 
        "type": 12
      },
      "cell_map": [ 
        [ 5, 0], [14, 0], [23, 0], [32, 0], [ 0,10], [37,10], [ 0,11], [37,11], [ 5,21], [14,21], [23,21], [32,21]
      ]
    }
  },
  "viewer": [
    {
      "colors": [
        [179, 179, 255],
        [204, 204, 255],
        [230, 230, 255],
        [255, 255, 255],
        [255, 230, 230],
        [255, 204, 204],
        [255, 179, 179],
        [255, 255, 102],
        [204,  51, 255],
        [255,   0,   0],
        [255, 173,  51],
        [  0,   0,   0],
        [206, 212, 219]
      ],
      "breaks": [
        0, 
        0.5, 
        1.5, 
        2.5, 
        3.5, 
        4.5, 
        5.5, 
        6.5, 
        7.5, 
        8.5, 
        9.5, 
        10.5,
        11.5,
        12.5
      ],
      "field": "type"
    }
  ]
}
